speech_core/PCTKUSR64.dll
speech_core/SAAPI64.dll
speech_core/SpeechCore.cp313-win_amd64.pyd
speech_core/ZDSRAPI_x64.dll
speech_core/__init__.py
speech_core/__speech_common.py
speech_core/__speech_sapi.py
speech_core/jfwapi64.dll
speech_core/nvdaControllerClient64.dll
speechcore-1.1.1.dist-info/licenses/LICENSE
speechcore-1.1.1.dist-info/METADATA
speechcore-1.1.1.dist-info/WHEEL
speechcore-1.1.1.dist-info/top_level.txt
speechcore-1.1.1.dist-info/RECORD
